{"created_at": "Wed Oct 04 10:49:25 +0000 2017", "id": 915529285171122176, "id_str": "915529285171122176", "full_text": "Celine Dion pledges proceeds from the show at the Colosseum in Caesars Palace to the victim's families of the Route 91 Harvest country music festival shooting on October 3, 2017 in Las Vegas, Nevada.\n\n(CNN) \u2014\n\nAn emotional Celine Dion returned to the stage in Las Vegas on Tuesday night, two days after the city and the country were rocked by the deadliest mass shooting in modern American history.\n\nThe singer, who has had two long-running residencies in Vegas, the first in 2003, told the crowd proceeds from the night would go to the victims of Sunday\u2019s shooting at the Route 91 Harvest Festival and their families.\n\n\u201cTonight is very different,\u201d Dion said ahead of her show, according to videos taken by fans. \u201cAfter Sunday night\u2019s incredibly tragic event, all of us here find ourselves asking a similar question. For you, it\u2019s, \u2018Do we still go to Celine\u2019s show on Tuesday night, only two days after the nightmare?\u2019 For me, it\u2019s, \u2018Can I still do my show? Should I still do my show only two days after the nightmare?\u2019 These are difficult questions.\u201d\n\nDion said she ultimately decided to go on with her performances \u201cto show love and support for those who are affected.\u201d\n\n\u201cOn Sunday, we lost too many beautiful, innocent souls and so many are still suffering. But tonight, we are going to let these families know that we are supporting them and that we will help them through their tragic loss,\u201d she said. \u201cThey are going to need a lot of love, a ton of emotional support, as well as a great deal of financial aid.\u201d\n\nHer announcement that proceeds would be donated drew more than 30 seconds of applause from the crowd.\n\nDion also dedicate the show to the victims, their families, first responders, and doctors and nurses \u201cwho are working around the clock to save lives.\u201d\n\n\u201cI want you to know that you have made the right choice in being here tonight,\u201d she said.\n\nIn the aftermath of Sunday\u2019s shooting, which killed 58 and injured more than 500, fellow Vegas-based performer Jennifer Lopez canceled her shows through October 7, according to a statement obtained by Variety.\n\nJason Aldean, who was on stage when the shooting began, also canceled his shows through October 12.", "truncated": false, "display_text_range": [0, 90], "entities": {"hashtags": [], "symbols": [], "user_mentions": [], "urls": [{"url": "https://t.co/GhvCgsZ9OA", "expanded_url": "http://eonli.ne/2ynBGlo", "display_url": "eonli.ne/2ynBGlo", "indices": [67, 90]}]}, "source": "<a href=\"http://www.socialflow.com\" rel=\"nofollow\">SocialFlow</a>", "in_reply_to_status_id": null, "in_reply_to_status_id_str": null, "in_reply_to_user_id": null, "in_reply_to_user_id_str": null, "in_reply_to_screen_name": null, "user": {"id": 2883841, "id_str": "2883841", "name": "E! News", "screen_name": "enews", "location": "Hollywood, CA", "description": "Your source for entertainment news, celebrities and pop culture.", "url": "https://t.co/J6mkqdLswn", "entities": {"url": {"urls": [{"url": "https://t.co/J6mkqdLswn", "expanded_url": "http://www.eonline.com", "display_url": "eonline.com", "indices": [0, 23]}]}, "description": {"urls": []}}, "protected": false, "followers_count": 11789462, "friends_count": 112555, "listed_count": 32776, "created_at": "Thu Mar 29 19:42:27 +0000 2007", "favourites_count": 29144, "utc_offset": null, "time_zone": null, "geo_enabled": true, "verified": true, "statuses_count": 272496, "lang": null, "contributors_enabled": false, "is_translator": false, "is_translation_enabled": true, "profile_background_color": "FFFFFF", "profile_background_image_url": "http://abs.twimg.com/images/themes/theme1/bg.png", "profile_background_image_url_https": "https://abs.twimg.com/images/themes/theme1/bg.png", "profile_background_tile": false, "profile_image_url": "http://pbs.twimg.com/profile_images/1303834216187047936/HL6Gotwt_normal.jpg", "profile_image_url_https": "https://pbs.twimg.com/profile_images/1303834216187047936/HL6Gotwt_normal.jpg", "profile_banner_url": "https://pbs.twimg.com/profile_banners/2883841/1599697347", "profile_link_color": "00B0F0", "profile_sidebar_border_color": "000000", "profile_sidebar_fill_color": "F0F0F0", "profile_text_color": "0D0D0D", "profile_use_background_image": true, "has_extended_profile": false, "default_profile": false, "default_profile_image": false, "following": false, "follow_request_sent": false, "notifications": false, "translator_type": "none", "withheld_in_countries": []}, "geo": null, "coordinates": null, "place": null, "contributors": null, "is_quote_status": false, "retweet_count": 143, "favorite_count": 801, "favorited": false, "retweeted": false, "possibly_sensitive": false, "possibly_sensitive_appealable": false, "lang": "en"}